CHANGES.txt
README.txt
buildout.cfg
setup.py
z3c/__init__.py
z3c.recipe.perlpackage.egg-info/PKG-INFO
z3c.recipe.perlpackage.egg-info/SOURCES.txt
z3c.recipe.perlpackage.egg-info/dependency_links.txt
z3c.recipe.perlpackage.egg-info/entry_points.txt
z3c.recipe.perlpackage.egg-info/namespace_packages.txt
z3c.recipe.perlpackage.egg-info/requires.txt
z3c.recipe.perlpackage.egg-info/top_level.txt
z3c.recipe.perlpackage.egg-info/zip-safe
z3c/recipe/__init__.py
z3c/recipe/perlpackage/__init__.py