Metadata-Version: 1.0
Name: z3c.recipe.perlpackage
Version: 0.1
Summary: ZC Buildout recipe for installing a Perl package
Home-page: http://www.python.org/pypi/z3c.recipe.perlpackage
Author: Kevin Teague
Author-email: kevin@bud.ca
License: ZPL 2.1
Keywords: buildout
Platform: UNKNOWN
